  <Text Key="117E0A66">Gấu Mèo</Text>
  <Text Key="84142889">Cây Xương Rồng và Cây Mọng Nước với Chậu Hoa Sọc Đỏ Trắng</Text>
  <Text Key="C6F6D8B6">Cây Xương Rồng và Cây Mọng Nước với Chậu Hoa Xanh Vàng</Text>
  <Text Key="47556993">Cây Xương Rồng và Cây Mọng Nước với Chậu Hoa Có Hoa Trắng</Text>
  <Text Key="2D436950">Cây Xương Rồng và Cây Mọng Nước với Chậu Hoa Hồng Đỏ</Text>
  <Text Key="8E289C9D">Cây Xương Rồng và Cây Mọng Nước với Chậu Hoa Sọc Tím Xanh</Text>
  <Text Key="96FC503A">Cây Xương Rồng và Cây Mọng Nước với Chậu Hoa Xanh Lá và Hồng</Text>
  <Text Key="2034778F">Chim Dẽ</Text>
  <Text Key="E40D6924">Bồ Câu Trắng</Text>
  <Text Key="17837451">Bồ Câu</Text>
  <Text Key="1BA7FC7E">Hải Âu</Text>
  <Text Key="3F4CE72B">Gấu Trúc Không Buồn</Text>
  <Text Key="B0ADED8E">Gấu Đen Dễ Thương Rồi</Text>
  <Text Key="8037B87D">Gấu Bắc Cực Lạnh Giá</Text>
  <Text Key="E3F5C030">Chim Cánh Cụt Ấm Áp</Text>
  <Text Key="A9DFB687">Cáo Thẹn Thùng</Text>
  <Text Key="082EA91A">Mèo Nhà Đồ Trắng Đen Ngộ Nghĩnh</Text>
  <Text Key="FB877AE9">Mèo Nhà Xám Ngốc Nghếch</Text>
  <Text Key="CD2F287C">Ếch Dí Dỏm Màu Cam</Text>
  <Text Key="0D313C73">Ếch Dí Dỏm Màu Xanh</Text>
  <Text Key="CE94F99D">Heo Con Màu Xanh</Text>
  <Text Key="D768AD3A">Heo Con Màu Hồng</Text>
  <Text Key="3D500E27">Heo Con Cổ Điển</Text>
  <Text Key="667FAF31">Mèo Nhà Màu Tím</Text>
  <Text Key="1A02D204">Mèo Nhà Màu Cam</Text>
  <Text Key="0198DF97">Mèo Nhà Màu Đen</Text>
  <Text Key="5904576A">Chó Bẹp Màu Nâu</Text>
  <Text Key="A53A154D">Chó Bẹp Màu Xanh Nhạt</Text>
  <Text Key="6C4B45C0">Cú Màu Vàng</Text>
  <Text Key="EDB410C3">Cú Màu Xanh</Text>
  <Text Key="521E4EA6">Cá Mập Màu Xanh Hải Quân</Text>
  <Text Key="092FED39">Cá Mập Màu Xanh Nhạt</Text>
  <Text Key="D900735F">Lạc Đà Simoleon</Text>
  <Text Key="7D0E47BC">Lạc Đà Màu Tím</Text>
  <Text Key="68E41829">Lạc Đà Màu Xanh</Text>
  <Text Key="3396EE56">Lạc Đà Màu Xanh Lá</Text>
  <Text Key="63BB8DB3">Lạc Đà Màu Vàng</Text>
  <Text Key="E5231770">Lạc Đà Màu Đỏ</Text>
  <Text Key="49638CBD">Lạc Đà Màu Đen</Text>
  <Text Key="FE3AB35A">Lạc Đà Màu Trắng</Text>
  <Text Key="DA0397C4">Nhung Nước Mắt To Simoleon</Text>
  <Text Key="B3B81457">Nhung Nước Mắt To Màu Tím</Text>
  <Text Key="7258572A">Nhung Nước Mắt To Màu Xanh</Text>
  <Text Key="D2051F0D">Nhung Nước Mắt To Màu Xanh Lá</Text>
  <Text Key="758E5B80">Nhung Nước Mắt To Màu Vàng</Text>
  <Text Key="663D6783">Nhung Nước Mắt To Màu Đỏ</Text>
  <Text Key="CAA7A666">Nhung Nước Mắt To Màu Đen</Text>
  <Text Key="C75147F9">Nhung Nước Mắt To Màu Trắng</Text>
  <Text Key="5FCC0E32">Ếch Simoleon</Text>
  <Text Key="97CA0869">Ếch Màu Hồng</Text>
