    <TextStringDefinition InstanceID="0xBCB43717" TextString="Kể chuyện" />
    <TextStringDefinition InstanceID="0x69A88FB8" TextString="Lắng nghe câu chuyện ngớ ngẩn của {1.SimFirstName}" />
    <TextStringDefinition InstanceID="0x509C9AE8" TextString="Kể câu chuyện ngớ ngẩn" />
    <TextStringDefinition InstanceID="0xD647CB33" TextString="Nói về Siêu anh hùng" />
    <TextStringDefinition InstanceID="0x57AAE008" TextString="Nói về Jedi và Sith" />
    <TextStringDefinition InstanceID="0x7F134AC1" TextString="Nói về Công chúa" />
    <TextStringDefinition InstanceID="0x73666648" TextString="Nói về Màu sắc yêu thích" />
    <TextStringDefinition InstanceID="0xCE39C5B2" TextString="Nói về Khủng long" />
    <TextStringDefinition InstanceID="0x27D17836" TextString="Nói về Lợn đất" />
    <TextStringDefinition InstanceID="0x8A68BBDC" TextString="Nói về Ngày" />
    <TextStringDefinition InstanceID="0xE43096BD" TextString="Nói về Nghệ thuật" />
    <TextStringDefinition InstanceID="0x9DBD87C5" TextString="Đùa về Mông gà" />
    <TextStringDefinition InstanceID="0x3F2F5369" TextString="Đùa về Khỉ-thằn lằn" />
    <TextStringDefinition InstanceID="0x9AC2AA9A" TextString="Nói chuyện với Người lạ" />
    <TextStringDefinition InstanceID="0xB696110E" TextString="Bị {1.SimFirstName} ném đồ uống vào" />
    <TextStringDefinition InstanceID="0x853DBDB6" TextString="Ném đồ uống" />
    <TextStringDefinition InstanceID="0x12294D3A" TextString="Bị {1.SimFirstName} đe dọa" />
    <TextStringDefinition InstanceID="0x0E8478B2" TextString="Đe dọa" />
    <TextStringDefinition InstanceID="0x5E0D1E3A" TextString="Lời khen chân thành" />
    <TextStringDefinition InstanceID="0x40CF86B4" TextString="Được {1.SimFirstName} cảm ơn" />
    <TextStringDefinition InstanceID="0x6D77730B" TextString="Lắng nghe câu chuyện khó tin" />
    <TextStringDefinition InstanceID="0x766F3E9D" TextString="Kể câu chuyện khó tin" />
    <TextStringDefinition InstanceID="0x36862557" TextString="Kể về Vấn đề" />
    <TextStringDefinition InstanceID="0xC48B8260" TextString="{1.SimFirstName} đã nói với {0.SimFirstName} rằng khi {0.SimPronounSubjective} {S0.gets}{P0.get} lớn dần, những thứ khác nhau bắt đầu khiến {0.SimPronounObjective} quan tâm.\n\nNhưng, tất cả những gì {0.SimFirstName} nghe thấy là những điều vô nghĩa và một câu trả lời không đúng.\n\n{0.SimPronounSubjective|xxUpper} không thể mất {0.SimPronounPossessiveDependent} người bạn mới—không phải sớm như vậy! Rõ ràng {0.SimFirstName} sẽ phải giải quyết vấn đề này một mình." />
    <TextStringDefinition InstanceID="0x6AFC9659" TextString="Lắng nghe câu chuyện kinh ngạc" />
    <TextStringDefinition InstanceID="0x9CE35EFB" TextString="Kể câu chuyện kinh ngạc" />
    <TextStringDefinition InstanceID="0x91477547" TextString="Lắng nghe câu chuyện tưởng tượng" />
    <TextStringDefinition InstanceID="0xB2BFB274" TextString="Lắng nghe câu chuyện cười của {1.SimFirstName}" />
    <TextStringDefinition InstanceID="0x9A808584" TextString="Kể câu chuyện cười" />
    <TextStringDefinition InstanceID="0xAAC3F23F" TextString="Đùa về Chuối" />
    <TextStringDefinition InstanceID="0xD2D89158" TextString="Đùa về Động vật kỳ lạ" />
    <TextStringDefinition InstanceID="0x56DA7B9A" TextString="Đùa về Voi" />
    <TextStringDefinition InstanceID="0x3784411F" TextString="Đùa về Đồ ăn tệ" />
    <TextStringDefinition InstanceID="0xE54B60DB" TextString="Đùa về Giáo viên" />
    <TextStringDefinition InstanceID="0xF86F5DFF" TextString="Đùa về Toilet" />
    <TextStringDefinition InstanceID="0x4BC76F15" TextString="Đùa về Phô mai Nacho" />
    <TextStringDefinition InstanceID="0x9B3ABD36" TextString="Đùa về Mông gà" />
    <TextStringDefinition InstanceID="0xC11B010F" TextString="Đùa về Mũi" />
    <TextStringDefinition InstanceID="0x76345F90" TextString="Đùa về Hoạt hình" />
    <TextStringDefinition InstanceID="0xBF374D55" TextString="Lắng nghe câu chuyện cười của {1.SimFirstName}" />
    <TextStringDefinition InstanceID="0xCE7F2F17" TextString="Kể câu chuyện cười tục tĩu" />
    <TextStringDefinition InstanceID="0xF6642DA1" TextString="Lắng nghe câu chuyện thu hút" />
    <TextStringDefinition InstanceID="0x460D7FE3" TextString="Kể câu chuyện thu hút" />
    <TextStringDefinition InstanceID="0xFE767075" TextString="Kể một câu chuyện về Biển" />
    <TextStringDefinition InstanceID="0x164DDB28" TextString="Lắng nghe câu chuyện kịch tính" />
    <TextStringDefinition InstanceID="0x08BE0E78" TextString="Kể câu chuyện kịch tính" />
    <TextStringDefinition InstanceID="0x0150DA8B" TextString="Lắng nghe câu chuyện cười" />
    <TextStringDefinition InstanceID="0x6947DD1D" TextString="Kể câu chuyện cười tục tĩu" />
    <TextStringDefinition InstanceID="0x0837F670" TextString="Lắng nghe câu chuyện làm hài lòng đám đông" />
    <TextStringDefinition InstanceID="0xCD57CF00" TextString="Kể câu chuyện làm hài lòng đám đông" />
