  <Text Key="ECE4FBA6">Đức</Text>
  <Text Key="A216AD31">Gruzia</Text>
  <Text Key="092B7D80">Guiné-Bissau</Text>
  <Text Key="19F31B08">Gambia</Text>
  <Text Key="8F868204">Gabon</Text>
  <Text Key="0878F606">Lãnh thổ Phía Nam của Pháp</Text>
  <Text Key="1FF032FA">Pháp</Text>
  <Text Key="0A2B7F05">Polynesia thuộc Pháp</Text>
  <Text Key="03AD2B35">Phần Lan</Text>
  <Text Key="1E791979">Quần đảo Falkland [Malvinas]</Text>
  <Text Key="76A32133">Fiji</Text>
  <Text Key="0A2B7F1C">Quần đảo Faroe</Text>
  <Text Key="0A2B7F12">Guiana thuộc Pháp</Text>
  <Text Key="2243D196">Ethiopia</Text>
  <Text Key="3D680B3C">Estonia</Text>
  <Text Key="072B7ACF">El Salvador</Text>
  <Text Key="9245928F">Eritrea</Text>
  <Text Key="C5501D7C">Ai Cập</Text>
  <Text Key="072B7ADB">Guinea Xích Đạo</Text>
  <Text Key="FEE63744">Ecuador</Text>
  <Text Key="76859907">Cộng hòa Dân chủ Congo [Kinshasa]</Text>
  <Text Key="082B7C3D">Cộng hòa Dominica</Text>
  <Text Key="CCBC5CA5">Dominica</Text>
  <Text Key="EF967BAD">Djibouti</Text>
  <Text Key="2FEE06CB">Đan Mạch</Text>
  <Text Key="C9ADB392">Séc</Text>
  <Text Key="A509242D">Síp</Text>
  <Text Key="126DCD54">Quần đảo Cayman</Text>
  <Text Key="052B77E0">Cape Verde</Text>
  <Text Key="59BC2A80">Cuba</Text>
  <Text Key="AA021E86">Croatia</Text>
  <Text Key="052B77E4">Costa Rica</Text>
  <Text Key="34590757">Congo [Brazzaville]</Text>
  <Text Key="AC3FDEA3">Comoros</Text>
  <Text Key="81C76A59">Colombia</Text>
  <Text Key="3AFCA119">Quần đảo Cook</Text>
  <Text Key="206DE32E">Quần đảo Cocos (Keeling)</Text>
  <Text Key="052B77FF">Bờ Biển Ngà</Text>
  <Text Key="4E75E584">Trung Quốc</Text>
  <Text Key="4C75E2DA">Chile</Text>
  <Text Key="5AFF1205">Chad</Text>
  <Text Key="1A6DD9A7">Cộng hòa Trung Phi</Text>
  <Text Key="727EC60D">Canada</Text>
  <Text Key="ECE26B43">Cameroon</Text>
  <Text Key="4C76F885">Campuchia</Text>
  <Text Key="157010E4">Quần đảo Virgin thuộc Anh</Text>
  <Text Key="A3374D06">Burundi</Text>
  <Text Key="82905260">Bulgaria</Text>
  <Text Key="7FF93CE9">Brazil</Text>
  <Text Key="D229DEFA">Botswana</Text>
