  <Text Key="E8C3F891">Chó Bầy Iceland</Text>
  <Text Key="DB0D317E">Spitz Đức</Text>
  <Text Key="6B8EA7A6">Corgi Wales Cardigan</Text>
  <Text Key="759B1BBA">Cockapoo</Text>
  <Text Key="0DBBDAF0">English Toy Spaniel</Text>
  <Text Key="8F505426">Poodle Nhỏ</Text>
  <Text Key="0F200047">Parson Russell Terrier</Text>
  <Text Key="2EB53073">Bocker</Text>
  <Text Key="C4DD0BE4">Wheaten Terrier</Text>
  <Text Key="A29615FA">Labradoodle</Text>
  <Text Key="88318037">Bedlington Terrier</Text>
  <Text Key="D2472C3F">Canaan</Text>
  <Text Key="8597B73C">Chó lai Chow Lab</Text>
  <Text Key="D21B8A0D">Dingo</Text>
  <Text Key="576816C2">Great Pyrenees</Text>
  <Text Key="C54A5043">Kerry Blue Terrier</Text>
  <Text Key="F5BAD940">Norse Elk Shepherd</Text>
  <Text Key="FCA5F1E1">Shar Pei</Text>
  <Text Key="FA98E2A0">Tibetan Mastiff</Text>
  <Text Key="134F6537">Black Russian Terrier</Text>
  <Text Key="8EAD942C">Gấu trúc</Text>
  <Text Key="FE4A12FA">Phòng Vuông (Boong-ke)</Text>
  <Text Key="7A32B4DA">Phòng Vuông</Text>
  <Text Key="FB143C55">Phòng Tam Giác</Text>
  <Text Key="A8F49C32">Phòng Tròn (Cực Lớn)</Text>
  <Text Key="B1974D12">Phòng Tròn (Lớn)</Text>
  <Text Key="7868BD62">Phòng Tròn</Text>
  <Text Key="09DCB308">Phòng Bát Giác</Text>
  <Text Key="93914320">Phòng Vuông (Xoáy 45 độ)</Text>
  <Text Key="2759B3D9">Công cụ Phòng</Text>
  <Text Key="5208A446">Kéo để tạo phòng. Để xóa, giữ Ctrl và vẽ qua phòng hiện có. Trong chế độ vẽ, giữ Shift để chuyển sang Công cụ Tường.</Text>
  <Text Key="84AD4069">Công cụ Tường - B</Text>
  <Text Key="85199836">Kéo để vẽ tường. Để xóa, giữ Ctrl và vẽ qua tường hiện có. Trong chế độ vẽ, giữ Shift để chuyển sang Công cụ Phòng.</Text>
  <Text Key="63C8B858">Hồ bơi Tam Giác</Text>
  <Text Key="B7681501">Hồ bơi Vuông</Text>
  <Text Key="E83CD995">Hồ bơi Tròn (Cực Lớn)</Text>
  <Text Key="0663BEB5">Hồ bơi Tròn (Lớn)</Text>
  <Text Key="8BB03B05">Hồ bơi Tròn</Text>
  <Text Key="EBF4D7B7">Hồ bơi Bát Giác</Text>
  <Text Key="840EA1F8">Hồ bơi Vuông (Xoáy 45 độ)</Text>
  <Text Key="B742DA2D">Mẹo: Sau khi đặt hồ bơi, dùng mũi tên ngang để thay đổi kích thước, mũi tên cong để xoay, và nút đa mũi tên để di chuyển.</Text>
  <Text Key="A76159F2">Công cụ Hồ bơi</Text>
  <Text Key="C6672823">Mẹo: Nhấn và kéo để tạo hình hồ bơi mong muốn. Để xóa nhanh, giữ CTRL và vẽ qua hồ bơi hiện có.</Text>
  <Text Key="1F9E1519">Sau khi đặt nền cao, dùng mũi tên dọc để nâng hoặc hạ, mũi tên ngang để thay đổi kích thước, mũi tên cong để xoay, hoặc nút đa mũi tên để di chuyển.</Text>
  <Text Key="5DC5C518">Nền cao Tam Giác</Text>
  <Text Key="EC5B08D4">Nền cao Vuông</Text>
  <Text Key="F50D6E3A">Nền cao Tròn (Cực Lớn)</Text>
  <Text Key="7855CD9A">Nền cao Tròn (Lớn)</Text>
  <Text Key="EDBDF9AA">Nền cao Tròn</Text>
  <Text Key="97F3D630">Nền cao Bát Giác</Text>
